uw_canvas/VERSION
uw_canvas/__init__.py
uw_canvas/accounts.py
uw_canvas/admins.py
uw_canvas/analytics.py
uw_canvas/assignments.py
uw_canvas/authentications.py
uw_canvas/collaborations.py
uw_canvas/conversations.py
uw_canvas/courses.py
uw_canvas/dao.py
uw_canvas/developer_keys.py
uw_canvas/discussions.py
uw_canvas/enrollments.py
uw_canvas/external_tools.py
uw_canvas/files.py
uw_canvas/grading_standards.py
uw_canvas/lti_registrations.py
uw_canvas/media_objects.py
uw_canvas/models.py
uw_canvas/outcome_groups.py
uw_canvas/outcome_results.py
uw_canvas/outcomes.py
uw_canvas/quizzes.py
uw_canvas/reports.py
uw_canvas/roles.py
uw_canvas/rubrics.py
uw_canvas/sections.py
uw_canvas/sis_import.py
uw_canvas/submissions.py
uw_canvas/terms.py
uw_canvas/test.py
uw_canvas/users.py
uw_canvas/utilities.py
uw_canvas/resources/canvas/file/api/v1/courses_as_user_id_sis_user_id_9136CCB8F66711D5BE060004AC494FFE
uw_canvas/resources/canvas/file/api/v1/accounts/sis_account_id%3Auwcourse%3Aseattle%3Acse%3Acse
uw_canvas/resources/canvas/file/api/v1/accounts/1010101/sub_accounts
uw_canvas/resources/canvas/file/api/v1/accounts/12345/admins_page_2_per_page_10
uw_canvas/resources/canvas/file/api/v1/accounts/12345/external_tools.http-headers
uw_canvas/resources/canvas/file/api/v1/accounts/12345/external_tools_page_2_per_page_10
uw_canvas/resources/canvas/file/api/v1/accounts/12345/external_tools_page_2_per_page_10.http-headers
uw_canvas/resources/canvas/file/api/v1/accounts/12345/lti_registrations_include_overlaid_configuration
uw_canvas/resources/canvas/file/api/v1/accounts/12345/roles.http-headers
uw_canvas/resources/canvas/file/api/v1/accounts/12345/roles_page_2_per_page_10
uw_canvas/resources/canvas/file/api/v1/accounts/12345/roles_per_page_100_show_inherited_1
uw_canvas/resources/canvas/file/api/v1/accounts/12345/terms_per_page_500_workflow_state_all
uw_canvas/resources/canvas/file/api/v1/accounts/12345/developer_keys/index.html
uw_restclients_canvas-1.2.30.dist-info/licenses/LICENSE
uw_restclients_canvas-1.2.30.dist-info/METADATA
uw_restclients_canvas-1.2.30.dist-info/WHEEL
uw_restclients_canvas-1.2.30.dist-info/top_level.txt
uw_restclients_canvas-1.2.30.dist-info/RECORD
