Metadata-Version: 2.4
Name: UW-RestClients-Canvas
Version: 1.2.30
Summary: A library for connecting to the Canvas LMS API
Home-page: https://github.com/uw-it-aca/uw-restclients-canvas
Author: UW-IT Student & Educational Technology Services
Author-email: aca-it@uw.edu
License: Apache License, Version 2.0
Classifier: Intended Audience :: Developers
Classifier: License :: OSI Approved :: Apache Software License
Classifier: Operating System :: OS Independent
Classifier: Programming Language :: Python
License-File: LICENSE
Requires-Dist: uw-restclients-core
Requires-Dist: python-dateutil
Requires-Dist: mock
Dynamic: author
Dynamic: author-email
Dynamic: classifier
Dynamic: description
Dynamic: home-page
Dynamic: license
Dynamic: license-file
Dynamic: requires-dist
Dynamic: summary
